[
	{
		"name": "Leon Bridges - Good Thing 2XLP",
		"price": "$21.98",
		"pictures": {
			"main": "//images.urbanoutfitters.com/is/image/UrbanOutfitters/47692678_001_b?$medium$&qlt=80&fit=constrain",
			"alt": "//images.urbanoutfitters.com/is/image/UrbanOutfitters/47692678_001_b?$medium$&qlt=80&fit=constrain"
		},
		"badge": null,
		"colors": {
			"items": {
				"code": "001",
				"image": null
			}
		}
	},
	{
		"name": "Ice Cream Silicone iPhone 8/7/6 Plus Case",
		"price": "$20.00",
		"pictures": {
			"main": "//images.urbanoutfitters.com/is/image/UrbanOutfitters/46996161_095_b?$medium$&qlt=80&fit=constrain",
			"alt": "//images.urbanoutfitters.com/is/image/UrbanOutfitters/46996161_095_b?$medium$&qlt=80&fit=constrain"
		},
		"badge": null,
		"colors": {
			"items": {
				"code": "095",
				"image": "https://images.urbanoutfitters.com/is/image/UrbanOutfitters/46996161_095_s"
			}
		}
	},
	{
		"name": "Fujifilm Instax Mini Pink Lemonade Film",
		"price": "$20.00",
		"pictures": {
			"main": "//images.urbanoutfitters.com/is/image/UrbanOutfitters/46861787_066_b?$medium$&qlt=80&fit=constrain",
			"alt": "//images.urbanoutfitters.com/is/image/UrbanOutfitters/46861787_066_b?$medium$&qlt=80&fit=constrain"
		},
		"badge": null,
		"colors": {
			"items": {
				"code": "066",
				"image": "https://images.urbanoutfitters.com/is/image/UrbanOutfitters/46861787_066_s"
			}
		}
	},
	{
		"name": "Panic! At The Disco - Pray For The Wicked LP",
		"price": "$19.98",
		"pictures": {
			"main": "//images.urbanoutfitters.com/is/image/UrbanOutfitters/47628466_001_b?$medium$&qlt=80&fit=constrain",
			"alt": "//images.urbanoutfitters.com/is/image/UrbanOutfitters/47628466_001_b?$medium$&qlt=80&fit=constrain"
		},
		"badge": null,
		"colors": {
			"items": {
				"code": "001",
				"image": null
			}
		}
	},
	{
		"name": "UO_TUNE_IN Hex Splash-Proof Speaker",
		"price": "$69.00",
		"pictures": {
			"main": "//images.urbanoutfitters.com/is/image/UrbanOutfitters/45851615_030_b?$medium$&qlt=80&fit=constrain",
			"alt": "//images.urbanoutfitters.com/is/image/UrbanOutfitters/45851615_030_b?$medium$&qlt=80&fit=constrain"
		},
		"badge": null,
		"colors": {
			"items": {
				"code": "030",
				"image": "https://images.urbanoutfitters.com/is/image/UrbanOutfitters/45851615_030_s"
			}
		}
	},
	{
		"name": "Rainbow Star Silicone iPhone 8/7/6 Plus Case",
		"price": "$20.00",
		"pictures": {
			"main": "//images.urbanoutfitters.com/is/image/UrbanOutfitters/46997904_095_b?$medium$&qlt=80&fit=constrain",
			"alt": "//images.urbanoutfitters.com/is/image/UrbanOutfitters/46997904_095_b?$medium$&qlt=80&fit=constrain"
		},
		"badge": null,
		"colors": {
			"items": {
				"code": "095",
				"image": "https://images.urbanoutfitters.com/is/image/UrbanOutfitters/46997904_095_s"
			}
		}
	},
	{
		"name": "Smart Rope Pure Jump Rope",
		"price": "$60.00",
		"pictures": {
			"main": "//images.urbanoutfitters.com/is/image/UrbanOutfitters/47380118_001_b?$medium$&qlt=80&fit=constrain",
			"alt": "//images.urbanoutfitters.com/is/image/UrbanOutfitters/47380118_001_b?$medium$&qlt=80&fit=constrain"
		},
		"badge": "Online Only",
		"colors": {
			"items": {
				"code": "001",
				"image": "https://images.urbanoutfitters.com/is/image/UrbanOutfitters/47380118_001_s"
			}
		}
	},
	{
		"name": "Kanto YU4 Desktop Phono Preamp Speaker Set",
		"price": "$300.00",
		"pictures": {
			"main": "//images.urbanoutfitters.com/is/image/UrbanOutfitters/47167911_045_b?$medium$&qlt=80&fit=constrain",
			"alt": "//images.urbanoutfitters.com/is/image/UrbanOutfitters/47167911_045_b?$medium$&qlt=80&fit=constrain"
		},
		"badge": "Online Only",
		"colors": {
			"items": [
				{
					"code": "001",
					"image": "https://images.urbanoutfitters.com/is/image/UrbanOutfitters/47167911_001_s"
				},
				{
					"code": "004",
					"image": "https://images.urbanoutfitters.com/is/image/UrbanOutfitters/47167911_004_s"
				},
				{
					"code": "045",
					"image": "https://images.urbanoutfitters.com/is/image/UrbanOutfitters/47167911_045_s"
				},
				{
					"code": "024",
					"image": "https://images.urbanoutfitters.com/is/image/UrbanOutfitters/47167911_024_s"
				},
				{
					"code": "010",
					"image": "https://images.urbanoutfitters.com/is/image/UrbanOutfitters/47167911_010_s"
				}
			]
		}
	},
	{
		"name": "Recover Bloom iPhone 8/7/6 Plus Case",
		"price": "$24.00",
		"pictures": {
			"main": "//images.urbanoutfitters.com/is/image/UrbanOutfitters/loading-spacer?&fmt=png-alpha&wid=349&hei=523",
			"alt": "//images.urbanoutfitters.com/is/image/UrbanOutfitters/46825808_100_b?$medium$&qlt=80&fit=constrain"
		},
		"badge": null,
		"colors": {
			"items": {
				"code": "100",
				"image": "https://images.urbanoutfitters.com/is/image/UrbanOutfitters/46825808_100_s"
			}
		}
	},
	{
		"name": "Kanto YU2 Desktop Speaker Set",
		"price": "$200.00",
		"pictures": {
			"main": "//images.urbanoutfitters.com/is/image/UrbanOutfitters/loading-spacer?&fmt=png-alpha&wid=349&hei=523",
			"alt": "//images.urbanoutfitters.com/is/image/UrbanOutfitters/47167515_024_b?$medium$&qlt=80&fit=constrain"
		},
		"badge": "Online Only",
		"colors": {
			"items": [
				{
					"code": "004",
					"image": "https://images.urbanoutfitters.com/is/image/UrbanOutfitters/47167515_004_s"
				},
				{
					"code": "045",
					"image": null
				},
				{
					"code": "024",
					"image": "https://images.urbanoutfitters.com/is/image/UrbanOutfitters/47167515_024_s"
				},
				{
					"code": "010",
					"image": "https://images.urbanoutfitters.com/is/image/UrbanOutfitters/47167515_010_s"
				}
			]
		}
	},
	{
		"name": "Bacon + Eggs Googly Eye iPhone 8/7/6 Case",
		"price": "$20.00",
		"pictures": {
			"main": "//images.urbanoutfitters.com/is/image/UrbanOutfitters/loading-spacer?&fmt=png-alpha&wid=349&hei=523",
			"alt": "//images.urbanoutfitters.com/is/image/UrbanOutfitters/46997573_095_b?$medium$&qlt=80&fit=constrain"
		},
		"badge": null,
		"colors": {
			"items": {
				"code": "095",
				"image": "https://images.urbanoutfitters.com/is/image/UrbanOutfitters/46997573_095_s"
			}
		}
	},
	{
		"name": "Various Artists - Riverdale: Carrie The Musical Original Television Soundtrack Limited LP",
		"price": "$25.98",
		"pictures": {
			"main": "//images.urbanoutfitters.com/is/image/UrbanOutfitters/loading-spacer?&fmt=png-alpha&wid=349&hei=523",
			"alt": "//images.urbanoutfitters.com/is/image/UrbanOutfitters/47656277_001_b?$medium$&qlt=80&fit=constrain"
		},
		"badge": null,
		"colors": {
			"items": {
				"code": "001",
				"image": "https://images.urbanoutfitters.com/is/image/UrbanOutfitters/47656277_001_s"
			}
		}
	},
	{
		"name": "Wildflower Check Please iPhone 8/7/6 Case",
		"price": "$35.00",
		"pictures": {
			"main": "//images.urbanoutfitters.com/is/image/UrbanOutfitters/loading-spacer?&fmt=png-alpha&wid=349&hei=523",
			"alt": "//images.urbanoutfitters.com/is/image/UrbanOutfitters/46955340_009_b?$medium$&qlt=80&fit=constrain"
		},
		"badge": null,
		"colors": {
			"items": {
				"code": "009",
				"image": "https://images.urbanoutfitters.com/is/image/UrbanOutfitters/46955340_009_s"
			}
		}
	},
	{
		"name": "Popcorn Silicone iPhone 8/7/6 Plus Case",
		"price": "$20.00",
		"pictures": {
			"main": "//images.urbanoutfitters.com/is/image/UrbanOutfitters/loading-spacer?&fmt=png-alpha&wid=349&hei=523",
			"alt": "//images.urbanoutfitters.com/is/image/UrbanOutfitters/46996310_072_b?$medium$&qlt=80&fit=constrain"
		},
		"badge": "Online Only",
		"colors": {
			"items": {
				"code": "072",
				"image": null
			}
		}
	},
	{
		"name": "Charlie XCX - Number 1 Angel/Pop 2 Cassette Tape",
		"price": "$14.98",
		"pictures": {
			"main": "//images.urbanoutfitters.com/is/image/UrbanOutfitters/loading-spacer?&fmt=png-alpha&wid=349&hei=523",
			"alt": "//images.urbanoutfitters.com/is/image/UrbanOutfitters/47006309_000_b?$medium$&qlt=80&fit=constrain"
		},
		"badge": null,
		"colors": {
			"items": {
				"code": "000",
				"image": "https://images.urbanoutfitters.com/is/image/UrbanOutfitters/47006309_000_s"
			}
		}
	},
	{
		"name": "Mokuyobi Gadget Decal Set",
		"price": "$10.00",
		"pictures": {
			"main": "//images.urbanoutfitters.com/is/image/UrbanOutfitters/loading-spacer?&fmt=png-alpha&wid=349&hei=523",
			"alt": "//images.urbanoutfitters.com/is/image/UrbanOutfitters/47078506_095_b?$medium$&qlt=80&fit=constrain"
		},
		"badge": null,
		"colors": {
			"items": {
				"code": "095",
				"image": "https://images.urbanoutfitters.com/is/image/UrbanOutfitters/47078506_095_s"
			}
		}
	},
	{
		"name": "Wildflower Check Please iPhone 8/7/6 Plus Case",
		"price": "$38.00",
		"pictures": {
			"main": "//images.urbanoutfitters.com/is/image/UrbanOutfitters/loading-spacer?&fmt=png-alpha&wid=349&hei=523",
			"alt": "//images.urbanoutfitters.com/is/image/UrbanOutfitters/46955688_009_b?$medium$&qlt=80&fit=constrain"
		},
		"badge": null,
		"colors": {
			"items": {
				"code": "009",
				"image": "https://images.urbanoutfitters.com/is/image/UrbanOutfitters/46955688_009_s"
			}
		}
	},
	{
		"name": "Crosley Tourmaline Cruiser Bluetooth Record Player",
		"price": "$69.00",
		"pictures": {
			"main": "//images.urbanoutfitters.com/is/image/UrbanOutfitters/loading-spacer?&fmt=png-alpha&wid=349&hei=523",
			"alt": "//images.urbanoutfitters.com/is/image/UrbanOutfitters/47404728_045_b?$medium$&qlt=80&fit=constrain"
		},
		"badge": "Online Only",
		"colors": {
			"items": {
				"code": "045",
				"image": "https://images.urbanoutfitters.com/is/image/UrbanOutfitters/47404728_045_s"
			}
		}
	},
	{
		"name": "G-Eazy - The Beautiful & Damned 2XLP",
		"price": "$24.98",
		"pictures": {
			"main": "//images.urbanoutfitters.com/is/image/UrbanOutfitters/loading-spacer?&fmt=png-alpha&wid=349&hei=523",
			"alt": "//images.urbanoutfitters.com/is/image/UrbanOutfitters/47621941_000_b?$medium$&qlt=80&fit=constrain"
		},
		"badge": null,
		"colors": {
			"items": {
				"code": "000",
				"image": "https://images.urbanoutfitters.com/is/image/UrbanOutfitters/47621941_000_s"
			}
		}
	},
	{
		"name": "MOGU Ultrasonic Aromatherapy Diffuser Speaker",
		"price": "$60.00",
		"pictures": {
			"main": "//images.urbanoutfitters.com/is/image/UrbanOutfitters/loading-spacer?&fmt=png-alpha&wid=349&hei=523",
			"alt": "//images.urbanoutfitters.com/is/image/UrbanOutfitters/47368717_010_b?$medium$&qlt=80&fit=constrain"
		},
		"badge": null,
		"colors": {
			"items": {
				"code": "010",
				"image": null
			}
		}
	},
	{
		"name": "Wallows - Spring EP",
		"price": "$16.98",
		"pictures": {
			"main": "//images.urbanoutfitters.com/is/image/UrbanOutfitters/loading-spacer?&fmt=png-alpha&wid=349&hei=523",
			"alt": "//images.urbanoutfitters.com/is/image/UrbanOutfitters/47622022_000_b?$medium$&qlt=80&fit=constrain"
		},
		"badge": null,
		"colors": {
			"items": {
				"code": "000",
				"image": "https://images.urbanoutfitters.com/is/image/UrbanOutfitters/47622022_000_s"
			}
		}
	},
	{
		"name": "Violent Femmes - Violent Femmes Limited LP",
		"price": "$29.98",
		"pictures": {
			"main": "//images.urbanoutfitters.com/is/image/UrbanOutfitters/loading-spacer?&fmt=png-alpha&wid=349&hei=523",
			"alt": "//images.urbanoutfitters.com/is/image/UrbanOutfitters/47628276_080_b?$medium$&qlt=80&fit=constrain"
		},
		"badge": null,
		"colors": {
			"items": {
				"code": "080",
				"image": "https://images.urbanoutfitters.com/is/image/UrbanOutfitters/47628276_080_s"
			}
		}
	},
	{
		"name": "Oops A Daisy iPhone 8/7/6 Plus Case",
		"price": "$28.00",
		"pictures": {
			"main": "//images.urbanoutfitters.com/is/image/UrbanOutfitters/loading-spacer?&fmt=png-alpha&wid=349&hei=523",
			"alt": "//images.urbanoutfitters.com/is/image/UrbanOutfitters/46798153_100_b?$medium$&qlt=80&fit=constrain"
		},
		"badge": null,
		"colors": {
			"items": {
				"code": "100",
				"image": "https://images.urbanoutfitters.com/is/image/UrbanOutfitters/46798153_100_s"
			}
		}
	},
	{
		"name": "Dance Gavin Dance - Artificial Selection Limited LP",
		"price": "$25.98",
		"pictures": {
			"main": "//images.urbanoutfitters.com/is/image/UrbanOutfitters/loading-spacer?&fmt=png-alpha&wid=349&hei=523",
			"alt": "//images.urbanoutfitters.com/is/image/UrbanOutfitters/47628334_000_b?$medium$&qlt=80&fit=constrain"
		},
		"badge": null,
		"colors": {
			"items": {
				"code": "000",
				"image": "https://images.urbanoutfitters.com/is/image/UrbanOutfitters/47628334_000_s"
			}
		}
	},
	{
		"name": "Crosley Portfolio Record Player",
		"price": "$120.00",
		"pictures": {
			"main": "//images.urbanoutfitters.com/is/image/UrbanOutfitters/loading-spacer?&fmt=png-alpha&wid=349&hei=523",
			"alt": "//images.urbanoutfitters.com/is/image/UrbanOutfitters/47405378_001_b?$medium$&qlt=80&fit=constrain"
		},
		"badge": "Online Only",
		"colors": {
			"items": {
				"code": "001",
				"image": "https://images.urbanoutfitters.com/is/image/UrbanOutfitters/47405378_001_s"
			}
		}
	},
	{
		"name": "Mokuyobi Best Day Ever Embroidered Gadget Decal Set",
		"price": "$14.00",
		"pictures": {
			"main": "//images.urbanoutfitters.com/is/image/UrbanOutfitters/loading-spacer?&fmt=png-alpha&wid=349&hei=523",
			"alt": "//images.urbanoutfitters.com/is/image/UrbanOutfitters/47078563_095_b?$medium$&qlt=80&fit=constrain"
		},
		"badge": "Online Only",
		"colors": {
			"items": {
				"code": "095",
				"image": "https://images.urbanoutfitters.com/is/image/UrbanOutfitters/47078563_095_s"
			}
		}
	},
	{
		"name": "Mokuyobi Food Fight Embroidered Gadget Decal Set",
		"price": "$14.00",
		"pictures": {
			"main": "//images.urbanoutfitters.com/is/image/UrbanOutfitters/loading-spacer?&fmt=png-alpha&wid=349&hei=523",
			"alt": "//images.urbanoutfitters.com/is/image/UrbanOutfitters/47078613_095_b?$medium$&qlt=80&fit=constrain"
		},
		"badge": "Online Only",
		"colors": {
			"items": {
				"code": "095",
				"image": "https://images.urbanoutfitters.com/is/image/UrbanOutfitters/47078613_095_s"
			}
		}
	},
	{
		"name": "Popcorn Silicone iPhone 8/7/6 Case",
		"price": "$20.00",
		"pictures": {
			"main": "//images.urbanoutfitters.com/is/image/UrbanOutfitters/loading-spacer?&fmt=png-alpha&wid=349&hei=523",
			"alt": "//images.urbanoutfitters.com/is/image/UrbanOutfitters/46996302_072_b?$medium$&qlt=80&fit=constrain"
		},
		"badge": "Online Only",
		"colors": {
			"items": {
				"code": "072",
				"image": "https://images.urbanoutfitters.com/is/image/UrbanOutfitters/46996302_072_s"
			}
		}
	},
	{
		"name": "Kodak PRINTOMATIC Instant Digital Camera",
		"price": "$70.00",
		"pictures": {
			"main": "//images.urbanoutfitters.com/is/image/UrbanOutfitters/loading-spacer?&fmt=png-alpha&wid=349&hei=523",
			"alt": "//images.urbanoutfitters.com/is/image/UrbanOutfitters/47069315_072_b?$medium$&qlt=80&fit=constrain"
		},
		"badge": "New Colors Available",
		"colors": {
			"items": [
				{
					"code": "004",
					"image": "https://images.urbanoutfitters.com/is/image/UrbanOutfitters/47069315_004_s"
				},
				{
					"code": "072",
					"image": "https://images.urbanoutfitters.com/is/image/UrbanOutfitters/47069315_072_s"
				},
				{
					"code": "040",
					"image": "https://images.urbanoutfitters.com/is/image/UrbanOutfitters/47069315_040_s"
				}
			]
		}
	},
	{
		"name": "Crosley DIY Chalkboard Cruiser Bluetooth Record Player",
		"price": "$69.00",
		"pictures": {
			"main": "//images.urbanoutfitters.com/is/image/UrbanOutfitters/loading-spacer?&fmt=png-alpha&wid=349&hei=523",
			"alt": "//images.urbanoutfitters.com/is/image/UrbanOutfitters/46890810_001_b?$medium$&qlt=80&fit=constrain"
		},
		"badge": "Online Only",
		"colors": {
			"items": {
				"code": "001",
				"image": null
			}
		}
	},
	{
		"name": "Waterproof Mobile Beach Bag",
		"price": "$14.00",
		"pictures": {
			"main": "//images.urbanoutfitters.com/is/image/UrbanOutfitters/loading-spacer?&fmt=png-alpha&wid=349&hei=523",
			"alt": "//images.urbanoutfitters.com/is/image/UrbanOutfitters/46998019_103_b?$medium$&qlt=80&fit=constrain"
		},
		"badge": "Online Only",
		"colors": {
			"items": [
				{
					"code": "103",
					"image": "https://images.urbanoutfitters.com/is/image/UrbanOutfitters/46998019_103_s"
				},
				{
					"code": "066",
					"image": "https://images.urbanoutfitters.com/is/image/UrbanOutfitters/46998019_066_s"
				}
			]
		}
	},
	{
		"name": "Kodak PRINTOMATIC Instant Digital Camera",
		"price": "$70.00",
		"pictures": {
			"main": "//images.urbanoutfitters.com/is/image/UrbanOutfitters/loading-spacer?&fmt=png-alpha&wid=349&hei=523",
			"alt": "//images.urbanoutfitters.com/is/image/UrbanOutfitters/47069315_040_b?$medium$&qlt=80&fit=constrain"
		},
		"badge": "New Colors Available",
		"colors": {
			"items": [
				{
					"code": "004",
					"image": "https://images.urbanoutfitters.com/is/image/UrbanOutfitters/47069315_004_s"
				},
				{
					"code": "072",
					"image": "https://images.urbanoutfitters.com/is/image/UrbanOutfitters/47069315_072_s"
				},
				{
					"code": "040",
					"image": "https://images.urbanoutfitters.com/is/image/UrbanOutfitters/47069315_040_s"
				}
			]
		}
	},
	{
		"name": "Ice Cream Silicone iPhone 8/7/6 Case",
		"price": "$20.00",
		"pictures": {
			"main": "//images.urbanoutfitters.com/is/image/UrbanOutfitters/loading-spacer?&fmt=png-alpha&wid=349&hei=523",
			"alt": "//images.urbanoutfitters.com/is/image/UrbanOutfitters/46996153_095_b?$medium$&qlt=80&fit=constrain"
		},
		"badge": null,
		"colors": {
			"items": {
				"code": "095",
				"image": "https://images.urbanoutfitters.com/is/image/UrbanOutfitters/46996153_095_s"
			}
		}
	},
	{
		"name": "Crosley Coupe Record Player",
		"price": "$98.00",
		"pictures": {
			"main": "//images.urbanoutfitters.com/is/image/UrbanOutfitters/loading-spacer?&fmt=png-alpha&wid=349&hei=523",
			"alt": "//images.urbanoutfitters.com/is/image/UrbanOutfitters/47173661_004_b?$medium$&qlt=80&fit=constrain"
		},
		"badge": "Online Only",
		"colors": {
			"items": {
				"code": "004",
				"image": "https://images.urbanoutfitters.com/is/image/UrbanOutfitters/47173661_004_s"
			}
		}
	},
	{
		"name": "Rainbow Star Silicone iPhone 8/7/6 Case",
		"price": "$20.00",
		"pictures": {
			"main": "//images.urbanoutfitters.com/is/image/UrbanOutfitters/loading-spacer?&fmt=png-alpha&wid=349&hei=523",
			"alt": "//images.urbanoutfitters.com/is/image/UrbanOutfitters/46997862_095_b?$medium$&qlt=80&fit=constrain"
		},
		"badge": null,
		"colors": {
			"items": {
				"code": "095",
				"image": "https://images.urbanoutfitters.com/is/image/UrbanOutfitters/46997862_095_s"
			}
		}
	},
	{
		"name": "Kodak PRINTOMATIC Instant Digital Camera",
		"price": "$70.00",
		"pictures": {
			"main": "//images.urbanoutfitters.com/is/image/UrbanOutfitters/loading-spacer?&fmt=png-alpha&wid=349&hei=523",
			"alt": "//images.urbanoutfitters.com/is/image/UrbanOutfitters/47069315_004_b?$medium$&qlt=80&fit=constrain"
		},
		"badge": "New Colors Available",
		"colors": {
			"items": [
				{
					"code": "004",
					"image": "https://images.urbanoutfitters.com/is/image/UrbanOutfitters/47069315_004_s"
				},
				{
					"code": "072",
					"image": "https://images.urbanoutfitters.com/is/image/UrbanOutfitters/47069315_072_s"
				},
				{
					"code": "040",
					"image": "https://images.urbanoutfitters.com/is/image/UrbanOutfitters/47069315_040_s"
				}
			]
		}
	},
	{
		"name": "Waterproof Mobile Beach Bag",
		"price": "$14.00",
		"pictures": {
			"main": "//images.urbanoutfitters.com/is/image/UrbanOutfitters/loading-spacer?&fmt=png-alpha&wid=349&hei=523",
			"alt": "//images.urbanoutfitters.com/is/image/UrbanOutfitters/46998019_066_b?$medium$&qlt=80&fit=constrain"
		},
		"badge": "Online Only",
		"colors": {
			"items": [
				{
					"code": "103",
					"image": "https://images.urbanoutfitters.com/is/image/UrbanOutfitters/46998019_103_s"
				},
				{
					"code": "066",
					"image": "https://images.urbanoutfitters.com/is/image/UrbanOutfitters/46998019_066_s"
				}
			]
		}
	},
	{
		"name": "Crosley Dansette Bermuda USB Vinyl Record Player",
		"price": "$260.00",
		"pictures": {
			"main": "//images.urbanoutfitters.com/is/image/UrbanOutfitters/loading-spacer?&fmt=png-alpha&wid=349&hei=523",
			"alt": "//images.urbanoutfitters.com/is/image/UrbanOutfitters/47174305_060_b?$medium$&qlt=80&fit=constrain"
		},
		"badge": "Online Only",
		"colors": {
			"items": {
				"code": "060",
				"image": null
			}
		}
	},
	{
		"name": "Crosley S100 Stereo Powered Speaker Set",
		"price": "$210.00",
		"pictures": {
			"main": "//images.urbanoutfitters.com/is/image/UrbanOutfitters/loading-spacer?&fmt=png-alpha&wid=349&hei=523",
			"alt": "//images.urbanoutfitters.com/is/image/UrbanOutfitters/47174420_001_b?$medium$&qlt=80&fit=constrain"
		},
		"badge": "Online Only",
		"colors": {
			"items": {
				"code": "001",
				"image": "https://images.urbanoutfitters.com/is/image/UrbanOutfitters/47174420_001_s"
			}
		}
	},
	{
		"name": "Elvis Presley - Elvis: 30 #1 Hits 2XLP",
		"price": "$34.98",
		"pictures": {
			"main": "//images.urbanoutfitters.com/is/image/UrbanOutfitters/loading-spacer?&fmt=png-alpha&wid=349&hei=523",
			"alt": "//images.urbanoutfitters.com/is/image/UrbanOutfitters/47472931_001_b?$medium$&qlt=80&fit=constrain"
		},
		"badge": null,
		"colors": {
			"items": {
				"code": "001",
				"image": "https://images.urbanoutfitters.com/is/image/UrbanOutfitters/47472931_001_s"
			}
		}
	},
	{
		"name": "Daisy Mobile Ring Holder Kickstand",
		"price": "$10.00",
		"pictures": {
			"main": "//images.urbanoutfitters.com/is/image/UrbanOutfitters/loading-spacer?&fmt=png-alpha&wid=349&hei=523",
			"alt": "//images.urbanoutfitters.com/is/image/UrbanOutfitters/46997995_070_b?$medium$&qlt=80&fit=constrain"
		},
		"badge": "Online Only",
		"colors": {
			"items": [
				{
					"code": "070",
					"image": "https://images.urbanoutfitters.com/is/image/UrbanOutfitters/46997995_070_s"
				},
				{
					"code": "065",
					"image": "https://images.urbanoutfitters.com/is/image/UrbanOutfitters/46997995_065_s"
				}
			]
		}
	},
	{
		"name": "Arctic Monkeys - Tranquility Base Hotel & Casino LP",
		"price": "$21.98",
		"pictures": {
			"main": "//images.urbanoutfitters.com/is/image/UrbanOutfitters/loading-spacer?&fmt=png-alpha&wid=349&hei=523",
			"alt": "//images.urbanoutfitters.com/is/image/UrbanOutfitters/47536859_001_b?$medium$&qlt=80&fit=constrain"
		},
		"badge": null,
		"colors": {
			"items": {
				"code": "001",
				"image": "https://images.urbanoutfitters.com/is/image/UrbanOutfitters/47536859_001_s"
			}
		}
	},
	{
		"name": "Daisy Mobile Ring Holder Kickstand",
		"price": "$10.00",
		"pictures": {
			"main": "//images.urbanoutfitters.com/is/image/UrbanOutfitters/loading-spacer?&fmt=png-alpha&wid=349&hei=523",
			"alt": "//images.urbanoutfitters.com/is/image/UrbanOutfitters/46997995_065_b?$medium$&qlt=80&fit=constrain"
		},
		"badge": "Online Only",
		"colors": {
			"items": [
				{
					"code": "070",
					"image": "https://images.urbanoutfitters.com/is/image/UrbanOutfitters/46997995_070_s"
				},
				{
					"code": "065",
					"image": "https://images.urbanoutfitters.com/is/image/UrbanOutfitters/46997995_065_s"
				}
			]
		}
	},
	{
		"name": "iHome Vanity Mirror Speaker",
		"price": "$100.00",
		"pictures": {
			"main": "//images.urbanoutfitters.com/is/image/UrbanOutfitters/loading-spacer?&fmt=png-alpha&wid=349&hei=523",
			"alt": "//images.urbanoutfitters.com/is/image/UrbanOutfitters/46533139_010_b?$medium$&qlt=80&fit=constrain"
		},
		"badge": null,
		"colors": {
			"items": {
				"code": "010",
				"image": "https://images.urbanoutfitters.com/is/image/UrbanOutfitters/46533139_010_s"
			}
		}
	},
	{
		"name": "Smart Plug",
		"price": "$16.00",
		"pictures": {
			"main": "//images.urbanoutfitters.com/is/image/UrbanOutfitters/loading-spacer?&fmt=png-alpha&wid=349&hei=523",
			"alt": "//images.urbanoutfitters.com/is/image/UrbanOutfitters/43034412_010_b?$medium$&qlt=80&fit=constrain"
		},
		"badge": null,
		"colors": {
			"items": {
				"code": "010",
				"image": "https://images.urbanoutfitters.com/is/image/UrbanOutfitters/43034412_010_s"
			}
		}
	},
	{
		"name": "Lomography Konstruktor 35mm Camera DIY Kit",
		"price": "$40.00",
		"pictures": {
			"main": "//images.urbanoutfitters.com/is/image/UrbanOutfitters/loading-spacer?&fmt=png-alpha&wid=349&hei=523",
			"alt": "//images.urbanoutfitters.com/is/image/UrbanOutfitters/45106689_001_b?$medium$&qlt=80&fit=constrain"
		},
		"badge": null,
		"colors": {
			"items": {
				"code": "001",
				"image": "https://images.urbanoutfitters.com/is/image/UrbanOutfitters/45106689_001_s"
			}
		}
	},
	{
		"name": "Twin Shadow - Caer LP",
		"price": "$19.98",
		"pictures": {
			"main": "//images.urbanoutfitters.com/is/image/UrbanOutfitters/loading-spacer?&fmt=png-alpha&wid=349&hei=523",
			"alt": "//images.urbanoutfitters.com/is/image/UrbanOutfitters/47474291_100_b?$medium$&qlt=80&fit=constrain"
		},
		"badge": null,
		"colors": {
			"items": {
				"code": "100",
				"image": "https://images.urbanoutfitters.com/is/image/UrbanOutfitters/47474291_100_s"
			}
		}
	},
	{
		"name": "Mighty Sound Wireless Mini Panda Speaker With Selfie Remote",
		"price": "$20.00",
		"pictures": {
			"main": "//images.urbanoutfitters.com/is/image/UrbanOutfitters/loading-spacer?&fmt=png-alpha&wid=349&hei=523",
			"alt": "//images.urbanoutfitters.com/is/image/UrbanOutfitters/47082441_001_b?$medium$&qlt=80&fit=constrain"
		},
		"badge": null,
		"colors": {
			"items": {
				"code": "001",
				"image": "https://images.urbanoutfitters.com/is/image/UrbanOutfitters/47082441_001_s"
			}
		}
	},
	{
		"name": "James Horner - Titanic: Music From The Motion Picture Limited 2XLP",
		"price": "$34.98",
		"pictures": {
			"main": "//images.urbanoutfitters.com/is/image/UrbanOutfitters/loading-spacer?&fmt=png-alpha&wid=349&hei=523",
			"alt": "//images.urbanoutfitters.com/is/image/UrbanOutfitters/47326038_040_b?$medium$&qlt=80&fit=constrain"
		},
		"badge": null,
		"colors": {
			"items": {
				"code": "040",
				"image": null
			}
		}
	},
	{
		"name": "Happy Plugs Plus Earbud Headphones",
		"price": "$30.00",
		"pictures": {
			"main": "//images.urbanoutfitters.com/is/image/UrbanOutfitters/loading-spacer?&fmt=png-alpha&wid=349&hei=523",
			"alt": "//images.urbanoutfitters.com/is/image/UrbanOutfitters/47096599_030_e?$medium$&qlt=80&fit=constrain"
		},
		"badge": null,
		"colors": {
			"items": [
				{
					"code": "030",
					"image": null
				},
				{
					"code": "001",
					"image": "https://images.urbanoutfitters.com/is/image/UrbanOutfitters/47096599_001_s"
				},
				{
					"code": "065",
					"image": "https://images.urbanoutfitters.com/is/image/UrbanOutfitters/47096599_065_s"
				},
				{
					"code": "010",
					"image": "https://images.urbanoutfitters.com/is/image/UrbanOutfitters/47096599_010_s"
				}
			]
		}
	},
	{
		"name": "Blue Woven Lightning Cable",
		"price": "$18.00",
		"pictures": {
			"main": "//images.urbanoutfitters.com/is/image/UrbanOutfitters/loading-spacer?&fmt=png-alpha&wid=349&hei=523",
			"alt": "//images.urbanoutfitters.com/is/image/UrbanOutfitters/47028865_040_b?$medium$&qlt=80&fit=constrain"
		},
		"badge": null,
		"colors": {
			"items": {
				"code": "040",
				"image": "https://images.urbanoutfitters.com/is/image/UrbanOutfitters/47028865_040_s"
			}
		}
	},
	{
		"name": "Sloth Life iPhone 8/7/6 Case",
		"price": "$24.00",
		"pictures": {
			"main": "//images.urbanoutfitters.com/is/image/UrbanOutfitters/loading-spacer?&fmt=png-alpha&wid=349&hei=523",
			"alt": "//images.urbanoutfitters.com/is/image/UrbanOutfitters/47028766_100_b?$medium$&qlt=80&fit=constrain"
		},
		"badge": "Online Only",
		"colors": {
			"items": {
				"code": "100",
				"image": "https://images.urbanoutfitters.com/is/image/UrbanOutfitters/47028766_100_s"
			}
		}
	},
	{
		"name": "Mighty Sound Wireless Mini Kitty Speaker With Selfie Remote",
		"price": "$20.00",
		"pictures": {
			"main": "//images.urbanoutfitters.com/is/image/UrbanOutfitters/loading-spacer?&fmt=png-alpha&wid=349&hei=523",
			"alt": "//images.urbanoutfitters.com/is/image/UrbanOutfitters/47082458_004_b?$medium$&qlt=80&fit=constrain"
		},
		"badge": null,
		"colors": {
			"items": {
				"code": "004",
				"image": "https://images.urbanoutfitters.com/is/image/UrbanOutfitters/47082458_004_s"
			}
		}
	},
	{
		"name": "Checkerboard Lightning Cable",
		"price": "$18.00",
		"pictures": {
			"main": "//images.urbanoutfitters.com/is/image/UrbanOutfitters/loading-spacer?&fmt=png-alpha&wid=349&hei=523",
			"alt": "//images.urbanoutfitters.com/is/image/UrbanOutfitters/47028857_010_b?$medium$&qlt=80&fit=constrain"
		},
		"badge": null,
		"colors": {
			"items": {
				"code": "010",
				"image": "https://images.urbanoutfitters.com/is/image/UrbanOutfitters/47028857_010_s"
			}
		}
	},
	{
		"name": "Happy Plugs Plus Earbud Headphones",
		"price": "$30.00",
		"pictures": {
			"main": "//images.urbanoutfitters.com/is/image/UrbanOutfitters/loading-spacer?&fmt=png-alpha&wid=349&hei=523",
			"alt": "//images.urbanoutfitters.com/is/image/UrbanOutfitters/47096599_001_d?$medium$&qlt=80&fit=constrain"
		},
		"badge": null,
		"colors": {
			"items": [
				{
					"code": "030",
					"image": null
				},
				{
					"code": "001",
					"image": "https://images.urbanoutfitters.com/is/image/UrbanOutfitters/47096599_001_s"
				},
				{
					"code": "065",
					"image": "https://images.urbanoutfitters.com/is/image/UrbanOutfitters/47096599_065_s"
				},
				{
					"code": "010",
					"image": "https://images.urbanoutfitters.com/is/image/UrbanOutfitters/47096599_010_s"
				}
			]
		}
	},
	{
		"name": "Wildflower Baby Unicorn iPhone 8/7/6 Plus Case",
		"price": "$38.00",
		"pictures": {
			"main": "//images.urbanoutfitters.com/is/image/UrbanOutfitters/loading-spacer?&fmt=png-alpha&wid=349&hei=523",
			"alt": "//images.urbanoutfitters.com/is/image/UrbanOutfitters/46954541_030_b?$medium$&qlt=80&fit=constrain"
		},
		"badge": "Online Only",
		"colors": {
			"items": {
				"code": "030",
				"image": "https://images.urbanoutfitters.com/is/image/UrbanOutfitters/46954541_030_s"
			}
		}
	},
	{
		"name": "Various Artists - Space Jam: Music From and Inspired By The Motion Picture Limited 2XLP",
		"price": "$36.98",
		"pictures": {
			"main": "//images.urbanoutfitters.com/is/image/UrbanOutfitters/loading-spacer?&fmt=png-alpha&wid=349&hei=523",
			"alt": "//images.urbanoutfitters.com/is/image/UrbanOutfitters/47368634_000_b?$medium$&qlt=80&fit=constrain"
		},
		"badge": null,
		"colors": {
			"items": {
				"code": "000",
				"image": null
			}
		}
	},
	{
		"name": "Happy Plugs Plus Earbud Headphones",
		"price": "$30.00",
		"pictures": {
			"main": "//images.urbanoutfitters.com/is/image/UrbanOutfitters/loading-spacer?&fmt=png-alpha&wid=349&hei=523",
			"alt": "//images.urbanoutfitters.com/is/image/UrbanOutfitters/47096599_010_d?$medium$&qlt=80&fit=constrain"
		},
		"badge": null,
		"colors": {
			"items": [
				{
					"code": "030",
					"image": null
				},
				{
					"code": "001",
					"image": "https://images.urbanoutfitters.com/is/image/UrbanOutfitters/47096599_001_s"
				},
				{
					"code": "065",
					"image": "https://images.urbanoutfitters.com/is/image/UrbanOutfitters/47096599_065_s"
				},
				{
					"code": "010",
					"image": "https://images.urbanoutfitters.com/is/image/UrbanOutfitters/47096599_010_s"
				}
			]
		}
	},
	{
		"name": "Icon Phone Ring",
		"price": "$10.00",
		"pictures": {
			"main": "//images.urbanoutfitters.com/is/image/UrbanOutfitters/loading-spacer?&fmt=png-alpha&wid=349&hei=523",
			"alt": "//images.urbanoutfitters.com/is/image/UrbanOutfitters/46891321_030_b?$medium$&qlt=80&fit=constrain"
		},
		"badge": null,
		"colors": {
			"items": [
				{
					"code": "030",
					"image": "https://images.urbanoutfitters.com/is/image/UrbanOutfitters/46891321_030_s"
				},
				{
					"code": "060",
					"image": "https://images.urbanoutfitters.com/is/image/UrbanOutfitters/46891321_060_s"
				},
				{
					"code": "045",
					"image": "https://images.urbanoutfitters.com/is/image/UrbanOutfitters/46891321_045_s"
				}
			]
		}
	},
	{
		"name": "Bacon + Eggs Googly Eye iPhone 8/7/6 Plus Case",
		"price": "$20.00",
		"pictures": {
			"main": "//images.urbanoutfitters.com/is/image/UrbanOutfitters/loading-spacer?&fmt=png-alpha&wid=349&hei=523",
			"alt": "//images.urbanoutfitters.com/is/image/UrbanOutfitters/46997805_095_b?$medium$&qlt=80&fit=constrain"
		},
		"badge": null,
		"colors": {
			"items": {
				"code": "095",
				"image": "https://images.urbanoutfitters.com/is/image/UrbanOutfitters/46997805_095_s"
			}
		}
	},
	{
		"name": "Nintendo Switch + Game Bundle",
		"price": "$419.00",
		"pictures": {
			"main": "//images.urbanoutfitters.com/is/image/UrbanOutfitters/loading-spacer?&fmt=png-alpha&wid=349&hei=523",
			"alt": "//images.urbanoutfitters.com/is/image/UrbanOutfitters/46996047_095_b?$medium$&qlt=80&fit=constrain"
		},
		"badge": "Online Only",
		"colors": {
			"items": {
				"code": "095",
				"image": "https://images.urbanoutfitters.com/is/image/UrbanOutfitters/46996047_095_s"
			}
		}
	},
	{
		"name": "Retro Shoebox Cassette Tape Recorder + USB Player",
		"price": "$50.00",
		"pictures": {
			"main": "//images.urbanoutfitters.com/is/image/UrbanOutfitters/loading-spacer?&fmt=png-alpha&wid=349&hei=523",
			"alt": "//images.urbanoutfitters.com/is/image/UrbanOutfitters/47096862_001_b?$medium$&qlt=80&fit=constrain"
		},
		"badge": null,
		"colors": {
			"items": {
				"code": "001",
				"image": null
			}
		}
	},
	{
		"name": "Universal Tablet Mount",
		"price": "$28.00",
		"pictures": {
			"main": "//images.urbanoutfitters.com/is/image/UrbanOutfitters/loading-spacer?&fmt=png-alpha&wid=349&hei=523",
			"alt": "//images.urbanoutfitters.com/is/image/UrbanOutfitters/46742946_001_b?$medium$&qlt=80&fit=constrain"
		},
		"badge": "Online Only",
		"colors": {
			"items": {
				"code": "001",
				"image": null
			}
		}
	},
	{
		"name": "Polaroid Originals Refurbished 600 96 Cam Fresh Red Instant Camera",
		"price": "$190.00",
		"pictures": {
			"main": "//images.urbanoutfitters.com/is/image/UrbanOutfitters/loading-spacer?&fmt=png-alpha&wid=349&hei=523",
			"alt": "//images.urbanoutfitters.com/is/image/UrbanOutfitters/46891628_060_b?$medium$&qlt=80&fit=constrain"
		},
		"badge": "Online Only",
		"colors": {
			"items": {
				"code": "060",
				"image": null
			}
		}
	},
	{
		"name": "Polaroid Originals Refurbished 600 96 Cam Fresh Blue Instant Camera",
		"price": "$190.00",
		"pictures": {
			"main": "//images.urbanoutfitters.com/is/image/UrbanOutfitters/loading-spacer?&fmt=png-alpha&wid=349&hei=523",
			"alt": "//images.urbanoutfitters.com/is/image/UrbanOutfitters/46891610_040_b?$medium$&qlt=80&fit=constrain"
		},
		"badge": "Online Only",
		"colors": {
			"items": {
				"code": "040",
				"image": "https://images.urbanoutfitters.com/is/image/UrbanOutfitters/46891610_040_s"
			}
		}
	},
	{
		"name": "Various Artists - Black Panther The Album: Music From And Inspired By Limited 2XLP",
		"price": "$34.98",
		"pictures": {
			"main": "//images.urbanoutfitters.com/is/image/UrbanOutfitters/loading-spacer?&fmt=png-alpha&wid=349&hei=523",
			"alt": "//images.urbanoutfitters.com/is/image/UrbanOutfitters/47268461_030_b?$medium$&qlt=80&fit=constrain"
		},
		"badge": null,
		"colors": {
			"items": {
				"code": "030",
				"image": "https://images.urbanoutfitters.com/is/image/UrbanOutfitters/47268461_030_s"
			}
		}
	},
	{
		"name": "ROAR Athena Safety Wearable Device",
		"price": "$130.00",
		"pictures": {
			"main": "//images.urbanoutfitters.com/is/image/UrbanOutfitters/loading-spacer?&fmt=png-alpha&wid=349&hei=523",
			"alt": "//images.urbanoutfitters.com/is/image/UrbanOutfitters/46941944_001_b?$medium$&qlt=80&fit=constrain"
		},
		"badge": "Online Only",
		"colors": {
			"items": {
				"code": "001",
				"image": null
			}
		}
	},
	{
		"name": "Various Artists - Coco Original Motion Picture Soundtrack Picture Disc LP",
		"price": "$21.98",
		"pictures": {
			"main": "//images.urbanoutfitters.com/is/image/UrbanOutfitters/loading-spacer?&fmt=png-alpha&wid=349&hei=523",
			"alt": "//images.urbanoutfitters.com/is/image/UrbanOutfitters/47250725_000_b?$medium$&qlt=80&fit=constrain"
		},
		"badge": null,
		"colors": {
			"items": {
				"code": "000",
				"image": "https://images.urbanoutfitters.com/is/image/UrbanOutfitters/47250725_000_s"
			}
		}
	},
	{
		"name": "Wildflower Baby Unicorn iPhone 8/7/6 Case",
		"price": "$35.00",
		"pictures": {
			"main": "//images.urbanoutfitters.com/is/image/UrbanOutfitters/loading-spacer?&fmt=png-alpha&wid=349&hei=523",
			"alt": "//images.urbanoutfitters.com/is/image/UrbanOutfitters/46954509_030_b?$medium$&qlt=80&fit=constrain"
		},
		"badge": "Online Only",
		"colors": {
			"items": {
				"code": "030",
				"image": "https://images.urbanoutfitters.com/is/image/UrbanOutfitters/46954509_030_s"
			}
		}
	},
	{
		"name": "Various Artists - Fifty Shades Freed Original Motion Picture Soundtrack 2XLP",
		"price": "$39.98",
		"pictures": {
			"main": "//images.urbanoutfitters.com/is/image/UrbanOutfitters/loading-spacer?&fmt=png-alpha&wid=349&hei=523",
			"alt": "//images.urbanoutfitters.com/is/image/UrbanOutfitters/47250907_001_b?$medium$&qlt=80&fit=constrain"
		},
		"badge": null,
		"colors": {
			"items": {
				"code": "001",
				"image": "https://images.urbanoutfitters.com/is/image/UrbanOutfitters/47250907_001_s"
			}
		}
	},
	{
		"name": "James Bay - Electric Light LP",
		"price": "$21.98",
		"pictures": {
			"main": "//images.urbanoutfitters.com/is/image/UrbanOutfitters/loading-spacer?&fmt=png-alpha&wid=349&hei=523",
			"alt": "//images.urbanoutfitters.com/is/image/UrbanOutfitters/47253851_001_b?$medium$&qlt=80&fit=constrain"
		},
		"badge": null,
		"colors": {
			"items": {
				"code": "001",
				"image": "https://images.urbanoutfitters.com/is/image/UrbanOutfitters/47253851_001_s"
			}
		}
	},
	{
		"name": "Lomography Lomo’Instant Square Camera",
		"price": "$229.00",
		"pictures": {
			"main": "//images.urbanoutfitters.com/is/image/UrbanOutfitters/loading-spacer?&fmt=png-alpha&wid=349&hei=523",
			"alt": "//images.urbanoutfitters.com/is/image/UrbanOutfitters/47006044_061_b?$medium$&qlt=80&fit=constrain"
		},
		"badge": "Online Only",
		"colors": {
			"items": {
				"code": "061",
				"image": "https://images.urbanoutfitters.com/is/image/UrbanOutfitters/47006044_061_s"
			}
		}
	},
	{
		"name": "Thirty Seconds to Mars - America Limited Cassette Tape",
		"price": "$12.98",
		"pictures": {
			"main": "//images.urbanoutfitters.com/is/image/UrbanOutfitters/loading-spacer?&fmt=png-alpha&wid=349&hei=523",
			"alt": "//images.urbanoutfitters.com/is/image/UrbanOutfitters/47267653_074_b?$medium$&qlt=80&fit=constrain"
		},
		"badge": null,
		"colors": {
			"items": {
				"code": "074",
				"image": "https://images.urbanoutfitters.com/is/image/UrbanOutfitters/47267653_074_s"
			}
		}
	},
	{
		"name": "Elohim - Elohim LP",
		"price": "$21.98",
		"pictures": {
			"main": "//images.urbanoutfitters.com/is/image/UrbanOutfitters/loading-spacer?&fmt=png-alpha&wid=349&hei=523",
			"alt": "//images.urbanoutfitters.com/is/image/UrbanOutfitters/47320742_001_b?$medium$&qlt=80&fit=constrain"
		},
		"badge": null,
		"colors": {
			"items": {
				"code": "001",
				"image": "https://images.urbanoutfitters.com/is/image/UrbanOutfitters/47320742_001_s"
			}
		}
	},
	{
		"name": "Beach House - 7 LP",
		"price": "$19.98",
		"pictures": {
			"main": "//images.urbanoutfitters.com/is/image/UrbanOutfitters/loading-spacer?&fmt=png-alpha&wid=349&hei=523",
			"alt": "//images.urbanoutfitters.com/is/image/UrbanOutfitters/47321310_001_b?$medium$&qlt=80&fit=constrain"
		},
		"badge": null,
		"colors": {
			"items": {
				"code": "001",
				"image": "https://images.urbanoutfitters.com/is/image/UrbanOutfitters/47321310_001_s"
			}
		}
	},
	{
		"name": "PopSockets Patterned Phone Stand",
		"price": "$10.00",
		"pictures": {
			"main": "//images.urbanoutfitters.com/is/image/UrbanOutfitters/loading-spacer?&fmt=png-alpha&wid=349&hei=523",
			"alt": "//images.urbanoutfitters.com/is/image/UrbanOutfitters/46954301_010_b?$medium$&qlt=80&fit=constrain"
		},
		"badge": null,
		"colors": {
			"items": {
				"code": "009",
				"image": "https://images.urbanoutfitters.com/is/image/UrbanOutfitters/46954301_009_s"
			}
		}
	},
	{
		"name": "Pink Floyd - Relics LP",
		"price": "$27.98",
		"pictures": {
			"main": "//images.urbanoutfitters.com/is/image/UrbanOutfitters/loading-spacer?&fmt=png-alpha&wid=349&hei=523",
			"alt": "//images.urbanoutfitters.com/is/image/UrbanOutfitters/47323993_001_b?$medium$&qlt=80&fit=constrain"
		},
		"badge": null,
		"colors": {
			"items": {
				"code": "001",
				"image": null
			}
		}
	},
	{
		"name": "ODESZA - A Moment Apart 2XLP",
		"price": "$25.98",
		"pictures": {
			"main": "//images.urbanoutfitters.com/is/image/UrbanOutfitters/loading-spacer?&fmt=png-alpha&wid=349&hei=523",
			"alt": "//images.urbanoutfitters.com/is/image/UrbanOutfitters/47338561_001_b?$medium$&qlt=80&fit=constrain"
		},
		"badge": null,
		"colors": {
			"items": {
				"code": "001",
				"image": "https://images.urbanoutfitters.com/is/image/UrbanOutfitters/47338561_001_s"
			}
		}
	},
	{
		"name": "Dashboard Confessional - Alter The Ending Limited LP",
		"price": "$26.98",
		"pictures": {
			"main": "//images.urbanoutfitters.com/is/image/UrbanOutfitters/loading-spacer?&fmt=png-alpha&wid=349&hei=523",
			"alt": "//images.urbanoutfitters.com/is/image/UrbanOutfitters/47339635_060_b?$medium$&qlt=80&fit=constrain"
		},
		"badge": null,
		"colors": {
			"items": {
				"code": "060",
				"image": "https://images.urbanoutfitters.com/is/image/UrbanOutfitters/47339635_060_s"
			}
		}
	},
	{
		"name": "Lomography The Lomo’Instant Square Camera",
		"price": "$199.00",
		"pictures": {
			"main": "//images.urbanoutfitters.com/is/image/UrbanOutfitters/loading-spacer?&fmt=png-alpha&wid=349&hei=523",
			"alt": "//images.urbanoutfitters.com/is/image/UrbanOutfitters/47005970_010_b?$medium$&qlt=80&fit=constrain"
		},
		"badge": "Online Only",
		"colors": {
			"items": {
				"code": "010",
				"image": "https://images.urbanoutfitters.com/is/image/UrbanOutfitters/47005970_010_s"
			}
		}
	},
	{
		"name": "CHVRCHES - Love Is Dead Limited Cassette Tape",
		"price": "$11.98",
		"pictures": {
			"main": "//images.urbanoutfitters.com/is/image/UrbanOutfitters/loading-spacer?&fmt=png-alpha&wid=349&hei=523",
			"alt": "//images.urbanoutfitters.com/is/image/UrbanOutfitters/47340765_001_b?$medium$&qlt=80&fit=constrain"
		},
		"badge": null,
		"colors": {
			"items": {
				"code": "001",
				"image": "https://images.urbanoutfitters.com/is/image/UrbanOutfitters/47340765_001_s"
			}
		}
	},
	{
		"name": "BUQU Watermelon Portable Power Bank",
		"price": "$20.00",
		"pictures": {
			"main": "//images.urbanoutfitters.com/is/image/UrbanOutfitters/loading-spacer?&fmt=png-alpha&wid=349&hei=523",
			"alt": "//images.urbanoutfitters.com/is/image/UrbanOutfitters/46912390_030_b?$medium$&qlt=80&fit=constrain"
		},
		"badge": null,
		"colors": {
			"items": {
				"code": "030",
				"image": "https://images.urbanoutfitters.com/is/image/UrbanOutfitters/46912390_030_s"
			}
		}
	},
	{
		"name": "Eminem - The Eminem Show Limited 2XLP",
		"price": "$29.98",
		"pictures": {
			"main": "//images.urbanoutfitters.com/is/image/UrbanOutfitters/loading-spacer?&fmt=png-alpha&wid=349&hei=523",
			"alt": "//images.urbanoutfitters.com/is/image/UrbanOutfitters/47323282_060_b?$medium$&qlt=80&fit=constrain"
		},
		"badge": null,
		"colors": {
			"items": {
				"code": "060",
				"image": "https://images.urbanoutfitters.com/is/image/UrbanOutfitters/47323282_060_s"
			}
		}
	},
	{
		"name": "PopSockets Metallic Diamonds Phone Stand",
		"price": "$15.00",
		"pictures": {
			"main": "//images.urbanoutfitters.com/is/image/UrbanOutfitters/loading-spacer?&fmt=png-alpha&wid=349&hei=523",
			"alt": "//images.urbanoutfitters.com/is/image/UrbanOutfitters/46953865_001_b?$medium$&qlt=80&fit=constrain"
		},
		"badge": null,
		"colors": {
			"items": [
				{
					"code": "001",
					"image": "https://images.urbanoutfitters.com/is/image/UrbanOutfitters/46953865_001_s"
				},
				{
					"code": "065",
					"image": "https://images.urbanoutfitters.com/is/image/UrbanOutfitters/46953865_065_s"
				},
				{
					"code": "046",
					"image": "https://images.urbanoutfitters.com/is/image/UrbanOutfitters/46953865_046_s"
				}
			]
		}
	},
	{
		"name": "Fujifilm Instax Mini Frame Sticker Set",
		"price": "$6.00",
		"pictures": {
			"main": "//images.urbanoutfitters.com/is/image/UrbanOutfitters/loading-spacer?&fmt=png-alpha&wid=349&hei=523",
			"alt": "//images.urbanoutfitters.com/is/image/UrbanOutfitters/47036710_095_b?$medium$&qlt=80&fit=constrain"
		},
		"badge": "Online Only",
		"colors": {
			"items": {
				"code": "095",
				"image": "https://images.urbanoutfitters.com/is/image/UrbanOutfitters/47036710_095_s"
			}
		}
	},
	{
		"name": "Daniel Caesar - Freudian Exclusive LP",
		"price": "$30.98",
		"pictures": {
			"main": "//images.urbanoutfitters.com/is/image/UrbanOutfitters/loading-spacer?&fmt=png-alpha&wid=349&hei=523",
			"alt": "//images.urbanoutfitters.com/is/image/UrbanOutfitters/47251954_045_b?$medium$&qlt=80&fit=constrain"
		},
		"badge": null,
		"colors": {
			"items": {
				"code": "045",
				"image": "https://images.urbanoutfitters.com/is/image/UrbanOutfitters/47251954_045_s"
			}
		}
	},
	{
		"name": "Velvet Caviar Blue Opal Portable Power Bank",
		"price": "$35.00",
		"pictures": {
			"main": "//images.urbanoutfitters.com/is/image/UrbanOutfitters/loading-spacer?&fmt=png-alpha&wid=349&hei=523",
			"alt": "//images.urbanoutfitters.com/is/image/UrbanOutfitters/46893376_040_b?$medium$&qlt=80&fit=constrain"
		},
		"badge": null,
		"colors": {
			"items": {
				"code": "040",
				"image": "https://images.urbanoutfitters.com/is/image/UrbanOutfitters/46893376_040_s"
			}
		}
	},
	{
		"name": "Fujifilm Fujicolor QuickSnap Flash 400 35MM Disposable Camera",
		"price": "$15.00",
		"pictures": {
			"main": "//images.urbanoutfitters.com/is/image/UrbanOutfitters/loading-spacer?&fmt=png-alpha&wid=349&hei=523",
			"alt": "//images.urbanoutfitters.com/is/image/UrbanOutfitters/46699708_095_b?$medium$&qlt=80&fit=constrain"
		},
		"badge": "Online Only",
		"colors": {
			"items": {
				"code": "095",
				"image": "https://images.urbanoutfitters.com/is/image/UrbanOutfitters/46699708_095_s"
			}
		}
	},
	{
		"name": "Recover Tie-Dye iPhone 8/7/6 Case",
		"price": "$20.00",
		"pictures": {
			"main": "//images.urbanoutfitters.com/is/image/UrbanOutfitters/loading-spacer?&fmt=png-alpha&wid=349&hei=523",
			"alt": "//images.urbanoutfitters.com/is/image/UrbanOutfitters/46876306_095_b?$medium$&qlt=80&fit=constrain"
		},
		"badge": "Online Only",
		"colors": {
			"items": {
				"code": "095",
				"image": "https://images.urbanoutfitters.com/is/image/UrbanOutfitters/46876306_095_s"
			}
		}
	},
	{
		"name": "Sonix Tamarindo Portable Power Bank",
		"price": "$45.00",
		"pictures": {
			"main": "//images.urbanoutfitters.com/is/image/UrbanOutfitters/loading-spacer?&fmt=png-alpha&wid=349&hei=523",
			"alt": "//images.urbanoutfitters.com/is/image/UrbanOutfitters/46868402_030_b?$medium$&qlt=80&fit=constrain"
		},
		"badge": null,
		"colors": {
			"items": {
				"code": "030",
				"image": "https://images.urbanoutfitters.com/is/image/UrbanOutfitters/46868402_030_s"
			}
		}
	},
	{
		"name": "Recover Skateboard iPhone 8/7/6 Plus Case",
		"price": "$30.00",
		"pictures": {
			"main": "//images.urbanoutfitters.com/is/image/UrbanOutfitters/loading-spacer?&fmt=png-alpha&wid=349&hei=523",
			"alt": "//images.urbanoutfitters.com/is/image/UrbanOutfitters/46879433_014_b?$medium$&qlt=80&fit=constrain"
		},
		"badge": null,
		"colors": {
			"items": {
				"code": "014",
				"image": "https://images.urbanoutfitters.com/is/image/UrbanOutfitters/46879433_014_s"
			}
		}
	},
	{
		"name": "Various Artists - Tank Girl Original Soundtrack From The United Artists Film Limited LP",
		"price": "$34.98",
		"pictures": {
			"main": "//images.urbanoutfitters.com/is/image/UrbanOutfitters/loading-spacer?&fmt=png-alpha&wid=349&hei=523",
			"alt": "//images.urbanoutfitters.com/is/image/UrbanOutfitters/47006184_070_b?$medium$&qlt=80&fit=constrain"
		},
		"badge": null,
		"colors": {
			"items": {
				"code": "070",
				"image": "https://images.urbanoutfitters.com/is/image/UrbanOutfitters/47006184_070_s"
			}
		}
	},
	{
		"name": "Velvet Caviar White Marble Portable Power Bank",
		"price": "$35.00",
		"pictures": {
			"main": "//images.urbanoutfitters.com/is/image/UrbanOutfitters/loading-spacer?&fmt=png-alpha&wid=349&hei=523",
			"alt": "//images.urbanoutfitters.com/is/image/UrbanOutfitters/46893285_010_b?$medium$&qlt=80&fit=constrain"
		},
		"badge": null,
		"colors": {
			"items": {
				"code": "010",
				"image": "https://images.urbanoutfitters.com/is/image/UrbanOutfitters/46893285_010_s"
			}
		}
	},
	{
		"name": "Velvet Caviar Cotton Candy Opal Portable Power Bank",
		"price": "$35.00",
		"pictures": {
			"main": "//images.urbanoutfitters.com/is/image/UrbanOutfitters/loading-spacer?&fmt=png-alpha&wid=349&hei=523",
			"alt": "//images.urbanoutfitters.com/is/image/UrbanOutfitters/46893384_066_b?$medium$&qlt=80&fit=constrain"
		},
		"badge": null,
		"colors": {
			"items": {
				"code": "066",
				"image": "https://images.urbanoutfitters.com/is/image/UrbanOutfitters/46893384_066_s"
			}
		}
	},
	{
		"name": "BUQU Chill Penguin Portable Power Bank",
		"price": "$20.00",
		"pictures": {
			"main": "//images.urbanoutfitters.com/is/image/UrbanOutfitters/loading-spacer?&fmt=png-alpha&wid=349&hei=523",
			"alt": "//images.urbanoutfitters.com/is/image/UrbanOutfitters/46912606_001_b?$medium$&qlt=80&fit=constrain"
		},
		"badge": null,
		"colors": {
			"items": {
				"code": "001",
				"image": "https://images.urbanoutfitters.com/is/image/UrbanOutfitters/46912606_001_s"
			}
		}
	},
	{
		"name": "Kacey Musgraves - Golden Hour LP",
		"price": "$21.98",
		"pictures": {
			"main": "//images.urbanoutfitters.com/is/image/UrbanOutfitters/loading-spacer?&fmt=png-alpha&wid=349&hei=523",
			"alt": "//images.urbanoutfitters.com/is/image/UrbanOutfitters/47079850_100_b?$medium$&qlt=80&fit=constrain"
		},
		"badge": "Online Only",
		"colors": {
			"items": {
				"code": "100",
				"image": "https://images.urbanoutfitters.com/is/image/UrbanOutfitters/47079850_100_s"
			}
		}
	}
]